{
  "generatedAt": "2026-03-30T21:04:44",
  "elapsedSeconds": 18,
  "alias": "",
  "programBreakdown": {
    "total": 32,
    "original": 0,
    "callExpanded": 0,
    "tableDiscovered": 0,
    "deprecated": 0,
    "classified": 32,
    "classifications": {
      "common-utility": 13,
      "batch-processing": 8,
      "main-ui": 4,
      "secondary-ui": 3,
      "validation-ui": 2,
      "unknown": 2
    }
  },
  "sqlTables": {
    "uniqueTables": 33,
    "totalSqlOperations": 101
  },
  "callGraph": {
    "totalCallEdges": 53,
    "totalCopyElements": 248,
    "totalFileIO": 23
  },
  "boundaryStats": {
    "database": "FKKONTO",
    "catalogQualified": 139,
    "programsRejected": 0,
    "sqlOpsStripped": 26
  },
  "cacheStats": {
    "extractionCacheHits": 32,
    "extractionCacheMisses": 0
  },
  "artifacts": [
    {
      "file": "all.json",
      "sizeKb": 3.5
    },
    {
      "file": "all_call_graph.json",
      "sizeKb": 5.7
    },
    {
      "file": "all_copy_elements.json",
      "sizeKb": 15.2
    },
    {
      "file": "all_file_io.json",
      "sizeKb": 10.1
    },
    {
      "file": "all_sql_tables.json",
      "sizeKb": 23.6
    },
    {
      "file": "all_total_programs.json",
      "sizeKb": 26.9
    },
    {
      "file": "business_areas.json",
      "sizeKb": 2.1
    },
    {
      "file": "db2_table_validation.json",
      "sizeKb": 4.4
    },
    {
      "file": "dependency_master.json",
      "sizeKb": 1524.5
    },
    {
      "file": "source_verification.json",
      "sizeKb": 158.9
    }
  ]
}