{
  "tableName": "PARAM_SATSER",
  "elementType": "sqltable",
  "lastUpdated": "2026-03-27T22:51:16",
  "db2Metadata": {
    "schemas": [
      "DBM"
    ],
    "type": "T",
    "tableRemarks": "DIV. PARAMETRE, LEGG TIL NYE KOL. V/BEHOV",
    "fetchedFrom": "BASISTST",
    "fetchedAt": "2026-03-27T22:51:16",
    "fetchMethod": "odbc",
    "columns": [
      {
        "colNo": 0,
        "name": "PARAM_KEY",
        "typeName": "CHARACTER",
        "length": 6,
        "scale": 0,
        "nullable": false,
        "remarks": ""
      },
      {
        "colNo": 1,
        "name": "FORSINK_RENTE",
        "typeName": "DECIMAL",
        "length": 5,
        "scale": 2,
        "nullable": false,
        "remarks": ""
      },
      {
        "colNo": 2,
        "name": "MIN_BELOP_KREDIT",
        "typeName": "DECIMAL",
        "length": 5,
        "scale": 2,
        "nullable": false,
        "remarks": ""
      },
      {
        "colNo": 3,
        "name": "MIN_BELOP_FAKTURA",
        "typeName": "DECIMAL",
        "length": 5,
        "scale": 2,
        "nullable": false,
        "remarks": ""
      },
      {
        "colNo": 4,
        "name": "FORSKNINGSAVGIFT",
        "typeName": "DECIMAL",
        "length": 5,
        "scale": 2,
        "nullable": false,
        "remarks": ""
      },
      {
        "colNo": 5,
        "name": "GRENSE_EHANDELSRABATT",
        "typeName": "DECIMAL",
        "length": 9,
        "scale": 2,
        "nullable": false,
        "remarks": ""
      },
      {
        "colNo": 6,
        "name": "MIN_EHANDELSRABATT",
        "typeName": "DECIMAL",
        "length": 9,
        "scale": 2,
        "nullable": false,
        "remarks": ""
      }
    ],
    "explicitForeignKeys": []
  }
}
