{
  "program": "RSFF032",
  "elementType": "cbl",
  "lastUpdated": "2026-03-27T22:53:50",
  "extraction": {
    "sourceHash": "sha256:0090e3349ad9d0a00a53f56e08682e9e445869a7857f3b7d3d7ed03d8ba5f4ba",
    "sourceType": "local-cbl",
    "sourcePath": "C:\\opt\\data\\VisualCobol\\Sources\\cbl\\rsff032.cbl",
    "actualName": "RSFF032",
    "program": "RSFF032",
    "copyElements": [
      {
        "name": "CURT.CPY",
        "type": "copybook"
      },
      {
        "name": "B912.CPY",
        "type": "copybook"
      },
      {
        "name": "GMAUTILS.CPY",
        "type": "copybook"
      },
      {
        "name": "VIEW.CPY",
        "type": "copybook"
      },
      {
        "name": "RSKONST.CPY",
        "type": "copybook"
      },
      {
        "name": "GMAPRTR.CPY",
        "type": "copybook"
      },
      {
        "name": "RSFVE02.CPX",
        "type": "cpx"
      },
      {
        "name": "GMFTRSA.CPY",
        "type": "copybook"
      },
      {
        "name": "KDL1.DCL",
        "type": "sql-declare"
      },
      {
        "name": "KDL3.DCL",
        "type": "sql-declare"
      },
      {
        "name": "KDL7.DCL",
        "type": "sql-declare"
      },
      {
        "name": "KDV1.DCL",
        "type": "sql-declare"
      },
      {
        "name": "KDT3.DCL",
        "type": "sql-declare"
      },
      {
        "name": "KKDY.DCL",
        "type": "sql-declare"
      },
      {
        "name": "KONT.DCL",
        "type": "sql-declare"
      },
      {
        "name": "KOLI.DCL",
        "type": "sql-declare"
      },
      {
        "name": "KDBE.DCL",
        "type": "sql-declare"
      },
      {
        "name": "KOST.DCL",
        "type": "sql-declare"
      },
      {
        "name": "KINF.DCL",
        "type": "sql-declare"
      },
      {
        "name": "KOTY.DCL",
        "type": "sql-declare"
      },
      {
        "name": "KSTA.DCL",
        "type": "sql-declare"
      },
      {
        "name": "TBRU.DCL",
        "type": "sql-declare"
      },
      {
        "name": "PST.DCL",
        "type": "sql-declare"
      },
      {
        "name": "KOM.DCL",
        "type": "sql-declare"
      },
      {
        "name": "VAR.DCL",
        "type": "sql-declare"
      },
      {
        "name": "KUN.DCL",
        "type": "sql-declare"
      },
      {
        "name": "TEK.DCL",
        "type": "sql-declare"
      },
      {
        "name": "AST.DCL",
        "type": "sql-declare"
      },
      {
        "name": "ART.DCL",
        "type": "sql-declare"
      },
      {
        "name": "SOH.DCL",
        "type": "sql-declare"
      },
      {
        "name": "SOL.DCL",
        "type": "sql-declare"
      },
      {
        "name": "LAG.DCL",
        "type": "sql-declare"
      },
      {
        "name": "ANL.DCL",
        "type": "sql-declare"
      },
      {
        "name": "AVTL.DCL",
        "type": "sql-declare"
      },
      {
        "name": "BIL.DCL",
        "type": "sql-declare"
      },
      {
        "name": "TA3.DCL",
        "type": "sql-declare"
      },
      {
        "name": "TSP.DCL",
        "type": "sql-declare"
      },
      {
        "name": "KDL2.DCL",
        "type": "sql-declare"
      },
      {
        "name": "TSA.DCL",
        "type": "sql-declare"
      },
      {
        "name": "DEFCPY.CPY",
        "type": "copybook"
      },
      {
        "name": "GMAVPRT.CPY",
        "type": "copybook"
      },
      {
        "name": "REQFELL.CPY",
        "type": "copybook"
      },
      {
        "name": "RSFF032.CPY",
        "type": "copybook"
      },
      {
        "name": "OAALOGG.CPX",
        "type": "cpx"
      },
      {
        "name": "RSFF032.CPB",
        "type": "copybook-binary"
      },
      {
        "name": "DSRUNNER.CPY",
        "type": "copybook"
      },
      {
        "name": "DSSYSINF.CPY",
        "type": "copybook"
      },
      {
        "name": "DS-CNTRL.MF",
        "type": "mf"
      }
    ],
    "sqlOperations": [
      {
        "schema": "C",
        "tableName": "AAR",
        "operation": "SELECT"
      },
      {
        "schema": "DBM",
        "tableName": "KD_VEKSTKONTROLL",
        "operation": "SELECT"
      },
      {
        "schema": "(UNQUALIFIED)",
        "tableName": "FKNR",
        "operation": "SELECT"
      },
      {
        "schema": "DBM",
        "tableName": "VAREREGISTER",
        "operation": "SELECT"
      },
      {
        "schema": "(UNQUALIFIED)",
        "tableName": "RECNO",
        "operation": "SELECT"
      },
      {
        "schema": "DBM",
        "tableName": "KD_LEV_FRA_FABRIKK",
        "operation": "SELECT"
      },
      {
        "schema": "A",
        "tableName": "RAAV_PARTINR",
        "operation": "SELECT"
      },
      {
        "schema": "(UNQUALIFIED)",
        "tableName": "VALUE",
        "operation": "SELECT"
      },
      {
        "schema": "DBM",
        "tableName": "KD_LEVERANSE",
        "operation": "SELECT"
      },
      {
        "schema": "DBM",
        "tableName": "KD_RAAVARE_PARTI",
        "operation": "SELECT"
      },
      {
        "schema": "(UNQUALIFIED)",
        "tableName": "LEV_RECNO",
        "operation": "SELECT"
      },
      {
        "schema": "DBM",
        "tableName": "KD_LEV_FEIL",
        "operation": "SELECT"
      },
      {
        "schema": "(UNQUALIFIED)",
        "tableName": "BILNR",
        "operation": "SELECT"
      },
      {
        "schema": "DBM",
        "tableName": "Z_BILER",
        "operation": "SELECT"
      },
      {
        "schema": "(UNQUALIFIED)",
        "tableName": "BRUKERID",
        "operation": "SELECT"
      },
      {
        "schema": "DBM",
        "tableName": "KD_TUNGA_BRUKER",
        "operation": "SELECT"
      },
      {
        "schema": "DBM",
        "tableName": "TRANSPORT",
        "operation": "SELECT"
      },
      {
        "schema": "DBM",
        "tableName": "TMS_SAAK_OPTIMA",
        "operation": "UPDATE"
      },
      {
        "schema": "DBM",
        "tableName": "KD_LEV_FRA_FABRIKK",
        "operation": "UPDATE"
      },
      {
        "schema": "DBM",
        "tableName": "KD_LEV_FRA_FABRIKK",
        "operation": "INSERT"
      },
      {
        "schema": "DBM",
        "tableName": "KD_LEV_FRA_FABRIKK",
        "operation": "DELETE"
      },
      {
        "schema": "(UNQUALIFIED)",
        "tableName": "FKNR_RAAVARE",
        "operation": "SELECT"
      },
      {
        "schema": "DBM",
        "tableName": "KD_RAAVARE_PARTI",
        "operation": "INSERT"
      },
      {
        "schema": "A",
        "tableName": "FKNR_RAAVARE",
        "operation": "SELECT"
      },
      {
        "schema": "DBM",
        "tableName": "KD_KONTRAKT_LIN",
        "operation": "SELECT"
      },
      {
        "schema": "DBM",
        "tableName": "TMS_SAAK_OPTIMA",
        "operation": "SELECT"
      },
      {
        "schema": "(UNQUALIFIED)",
        "tableName": "RAAV_PARTINR",
        "operation": "SELECT"
      },
      {
        "schema": "A",
        "tableName": "KUNDENR",
        "operation": "SELECT"
      },
      {
        "schema": "DBM",
        "tableName": "KUNDER",
        "operation": "SELECT"
      },
      {
        "schema": "(UNQUALIFIED)",
        "tableName": "AVDNAVN",
        "operation": "SELECT"
      },
      {
        "schema": "DBM",
        "tableName": "ANLEGG",
        "operation": "SELECT"
      },
      {
        "schema": "(UNQUALIFIED)",
        "tableName": "TEKST",
        "operation": "SELECT"
      },
      {
        "schema": "DBM",
        "tableName": "TEKSTER",
        "operation": "SELECT"
      },
      {
        "schema": "(UNQUALIFIED)",
        "tableName": "PRODNR",
        "operation": "SELECT"
      },
      {
        "schema": "(UNQUALIFIED)",
        "tableName": "VARENAVN",
        "operation": "SELECT"
      },
      {
        "schema": "A",
        "tableName": "BILNAVN",
        "operation": "SELECT"
      },
      {
        "schema": "(UNQUALIFIED)",
        "tableName": "KOMMUNENAVN",
        "operation": "SELECT"
      },
      {
        "schema": "DBM",
        "tableName": "Z_KOMMUNER",
        "operation": "SELECT"
      },
      {
        "schema": "B",
        "tableName": "KUNDENR",
        "operation": "SELECT"
      },
      {
        "schema": "DBM",
        "tableName": "KD_DYRKER",
        "operation": "SELECT"
      },
      {
        "schema": "(UNQUALIFIED)",
        "tableName": "RTRIM",
        "operation": "SELECT"
      },
      {
        "schema": "DBM",
        "tableName": "KD_KONTRAKT_TYPE",
        "operation": "SELECT"
      },
      {
        "schema": "DBM",
        "tableName": "ART",
        "operation": "SELECT"
      },
      {
        "schema": "FK",
        "tableName": "D10DMA",
        "operation": "SELECT"
      },
      {
        "schema": "DBM",
        "tableName": "KD_KONTRAKT_STATUS",
        "operation": "SELECT"
      },
      {
        "schema": "A",
        "tableName": "AREALNR",
        "operation": "SELECT"
      }
    ],
    "callTargets": [
      "GMACOCO",
      "RSVF032",
      "DSFUNKS",
      "GMFFELL",
      "GMAMEXT",
      "GMADATO",
      "D01B912",
      "GMFSQLF"
    ],
    "fileIO": [],
    "extractedAt": "2026-03-27T22:53:50"
  }
}
