{
  "program": "AABRABA7",
  "elementType": "cbl",
  "lastUpdated": "2026-03-27T23:11:58",
  "extraction": {
    "sourceHash": "sha256:d152be0126cce6050c23f7d346c62375b6b9a9f97594b785b837e918786f8849",
    "sourceType": "local-cbl",
    "sourcePath": "C:\\opt\\data\\VisualCobol\\Sources\\cbl\\AABRABA7.CBL",
    "actualName": "AABRABA7",
    "program": "AABRABA7",
    "copyElements": [
      {
        "name": "DEFCPY.CPY",
        "type": "copybook"
      },
      {
        "name": "REQFELL.CPY",
        "type": "copybook"
      },
      {
        "name": "VAR.DCL",
        "type": "sql-declare"
      },
      {
        "name": "VAR2.DCL",
        "type": "sql-declare"
      },
      {
        "name": "LEV.DCL",
        "type": "sql-declare"
      },
      {
        "name": "VHG.DCL",
        "type": "sql-declare"
      },
      {
        "name": "VGR.DCL",
        "type": "sql-declare"
      },
      {
        "name": "VAVA.DCL",
        "type": "sql-declare"
      }
    ],
    "sqlOperations": [
      {
        "schema": "V",
        "tableName": "VAREGR",
        "operation": "SELECT"
      },
      {
        "schema": "DBM",
        "tableName": "VAREREGISTER",
        "operation": "SELECT"
      },
      {
        "schema": "A",
        "tableName": "FKNR",
        "operation": "SELECT"
      },
      {
        "schema": "(UNQUALIFIED)",
        "tableName": "FKNR",
        "operation": "SELECT"
      },
      {
        "schema": "(UNQUALIFIED)",
        "tableName": "TEMP4",
        "operation": "SELECT"
      },
      {
        "schema": "(UNQUALIFIED)",
        "tableName": "VALUE",
        "operation": "SELECT"
      },
      {
        "schema": "DBM",
        "tableName": "VAREAVD",
        "operation": "SELECT"
      },
      {
        "schema": "DBM",
        "tableName": "A_VAREAVD",
        "operation": "SELECT"
      },
      {
        "schema": "(UNQUALIFIED)",
        "tableName": "TOLLTARIFFNR",
        "operation": "SELECT"
      },
      {
        "schema": "DBM",
        "tableName": "VAREREGISTER_DEL2",
        "operation": "SELECT"
      }
    ],
    "callTargets": [
      "GMACOCO",
      "GMFTRAP"
    ],
    "fileIO": [
      {
        "logicalName": "RCFILE",
        "physicalName": "AABRABA7.RC",
        "path": "N:\\COBNT",
        "fullPath": "N:\\COBNT\\AABRABA7.RC",
        "assignType": "literal",
        "operations": [
          "WRITE"
        ]
      },
      {
        "logicalName": "AVVIK-FIL",
        "physicalName": "VAREREG-UTTREKK.TXT",
        "path": "U:\\",
        "fullPath": "U:/VAREREG-UTTREKK.TXT",
        "assignType": "literal",
        "operations": [
          "WRITE"
        ]
      }
    ],
    "extractedAt": "2026-03-27T23:11:58"
  }
}
