{
  "tableName": "EGETBRUK_HODE",
  "elementType": "sqltable",
  "lastUpdated": "2026-03-27T23:12:25",
  "db2Metadata": {
    "schemas": [
      "DBM"
    ],
    "type": "T",
    "tableRemarks": "INNKJØP EGET BRUK",
    "fetchedFrom": "BASISTST",
    "fetchedAt": "2026-03-27T23:12:25",
    "fetchMethod": "mcp-http",
    "columns": [
      {
        "colNo": 0,
        "name": "AVDNR",
        "typeName": "DECIMAL",
        "length": 6,
        "scale": 0,
        "nullable": false,
        "remarks": ""
      },
      {
        "colNo": 1,
        "name": "ORDRENR",
        "typeName": "DECIMAL",
        "length": 8,
        "scale": 0,
        "nullable": false,
        "remarks": ""
      },
      {
        "colNo": 2,
        "name": "REGDATO",
        "typeName": "DECIMAL",
        "length": 8,
        "scale": 0,
        "nullable": false,
        "remarks": ""
      },
      {
        "colNo": 3,
        "name": "LEVNR",
        "typeName": "DECIMAL",
        "length": 6,
        "scale": 0,
        "nullable": false,
        "remarks": ""
      },
      {
        "colNo": 4,
        "name": "LEVNAVN",
        "typeName": "CHARACTER",
        "length": 32,
        "scale": 0,
        "nullable": false,
        "remarks": ""
      },
      {
        "colNo": 5,
        "name": "LEV_ADRESSE",
        "typeName": "CHARACTER",
        "length": 32,
        "scale": 0,
        "nullable": false,
        "remarks": ""
      },
      {
        "colNo": 6,
        "name": "LEV_POSTADR",
        "typeName": "CHARACTER",
        "length": 32,
        "scale": 0,
        "nullable": false,
        "remarks": ""
      },
      {
        "colNo": 7,
        "name": "SIGNATUR",
        "typeName": "CHARACTER",
        "length": 8,
        "scale": 0,
        "nullable": false,
        "remarks": ""
      },
      {
        "colNo": 8,
        "name": "SIGNATUR_NAVN",
        "typeName": "CHARACTER",
        "length": 32,
        "scale": 0,
        "nullable": false,
        "remarks": ""
      },
      {
        "colNo": 9,
        "name": "FORRETN_OMR",
        "typeName": "CHARACTER",
        "length": 3,
        "scale": 0,
        "nullable": false,
        "remarks": ""
      },
      {
        "colNo": 10,
        "name": "REFORDRE",
        "typeName": "DECIMAL",
        "length": 8,
        "scale": 0,
        "nullable": false,
        "remarks": ""
      },
      {
        "colNo": 11,
        "name": "SENDES_TEKST",
        "typeName": "VARCHAR",
        "length": 96,
        "scale": 0,
        "nullable": false,
        "remarks": ""
      }
    ],
    "explicitForeignKeys": []
  }
}
