{
  "tableName": "KD_BEIS",
  "elementType": "sqltable",
  "lastUpdated": "2026-03-27T23:12:25",
  "db2Metadata": {
    "schemas": [
      "DBM"
    ],
    "type": "T",
    "tableRemarks": "Kontraktdyrkersystemet: Beiseregister",
    "fetchedFrom": "BASISTST",
    "fetchedAt": "2026-03-27T23:12:25",
    "fetchMethod": "mcp-http",
    "columns": [
      {
        "colNo": 0,
        "name": "BEISENR",
        "typeName": "DECIMAL",
        "length": 4,
        "scale": 0,
        "nullable": false,
        "remarks": ""
      },
      {
        "colNo": 1,
        "name": "KORTTEKST",
        "typeName": "CHARACTER",
        "length": 10,
        "scale": 0,
        "nullable": false,
        "remarks": ""
      },
      {
        "colNo": 2,
        "name": "NAVN",
        "typeName": "CHARACTER",
        "length": 30,
        "scale": 0,
        "nullable": false,
        "remarks": ""
      },
      {
        "colNo": 3,
        "name": "DOSE",
        "typeName": "DECIMAL",
        "length": 8,
        "scale": 0,
        "nullable": false,
        "remarks": ""
      },
      {
        "colNo": 4,
        "name": "DOSERING",
        "typeName": "DECIMAL",
        "length": 8,
        "scale": 0,
        "nullable": false,
        "remarks": ""
      },
      {
        "colNo": 5,
        "name": "STATUS",
        "typeName": "DECIMAL",
        "length": 1,
        "scale": 0,
        "nullable": false,
        "remarks": ""
      },
      {
        "colNo": 6,
        "name": "SORTERING",
        "typeName": "DECIMAL",
        "length": 8,
        "scale": 0,
        "nullable": false,
        "remarks": ""
      },
      {
        "colNo": 7,
        "name": "AKTIV",
        "typeName": "DECIMAL",
        "length": 1,
        "scale": 0,
        "nullable": false,
        "remarks": ""
      },
      {
        "colNo": 8,
        "name": "BEISEKODE",
        "typeName": "CHARACTER",
        "length": 1,
        "scale": 0,
        "nullable": false,
        "remarks": ""
      },
      {
        "colNo": 9,
        "name": "BRUKERID",
        "typeName": "CHARACTER",
        "length": 8,
        "scale": 0,
        "nullable": false,
        "remarks": ""
      },
      {
        "colNo": 10,
        "name": "TIDSPUNKT",
        "typeName": "TIMESTAMP",
        "length": 10,
        "scale": 6,
        "nullable": false,
        "remarks": ""
      }
    ],
    "explicitForeignKeys": []
  }
}
