{
  "program": "RKHPLKO",
  "elementType": "cbl",
  "lastUpdated": "2026-03-27T22:41:07",
  "extraction": {
    "sourceHash": "sha256:b3ed849608dcade454b8bb530a922ad6c9b25150ce0bb68fcee1350e968dbadb",
    "sourceType": "local-cbl",
    "sourcePath": "C:\\opt\\data\\VisualCobol\\Sources\\cbl\\rkhplko.cbl",
    "actualName": "RKHPLKO",
    "program": "RKHPLKO",
    "copyElements": [
      {
        "name": "DEFCPY.CPY",
        "type": "copybook"
      },
      {
        "name": "REQFELL.CPY",
        "type": "copybook"
      },
      {
        "name": "RKHPLKO.CPB",
        "type": "copybook-binary"
      },
      {
        "name": "DSRUNNER.CPY",
        "type": "copybook"
      },
      {
        "name": "DSSYSINF.CPY",
        "type": "copybook"
      },
      {
        "name": "DS-CNTRL.MF",
        "type": "mf"
      }
    ],
    "sqlOperations": [],
    "callTargets": [
      "GMACOCO",
      "GMFFELL",
      "GMAMEXT",
      "GMFSQLF"
    ],
    "fileIO": [],
    "extractedAt": "2026-03-27T22:41:07"
  }
}
